odoo/addons/hr_calendar_rest_time/README.rst
odoo/addons/hr_calendar_rest_time/__init__.py
odoo/addons/hr_calendar_rest_time/__manifest__.py
odoo/addons/hr_calendar_rest_time/i18n/hr_calendar_rest_time.pot
odoo/addons/hr_calendar_rest_time/models/__init__.py
odoo/addons/hr_calendar_rest_time/models/resource_calendar_attendance.py
odoo/addons/hr_calendar_rest_time/models/resource_mixin.py
odoo/addons/hr_calendar_rest_time/readme/CONTRIBUTORS.rst
odoo/addons/hr_calendar_rest_time/readme/DESCRIPTION.rst
odoo/addons/hr_calendar_rest_time/readme/HISTORY.rst
odoo/addons/hr_calendar_rest_time/readme/USAGE.rst
odoo/addons/hr_calendar_rest_time/static/description/icon.png
odoo/addons/hr_calendar_rest_time/static/description/index.html
odoo/addons/hr_calendar_rest_time/tests/__init__.py
odoo/addons/hr_calendar_rest_time/tests/test_hr_calendar_rest_time.py
odoo/addons/hr_calendar_rest_time/views/resource_calendar_attendance.xml
odoo11_addon_hr_calendar_rest_time-11.0.1.0.0.99.dev5.dist-info/METADATA
odoo11_addon_hr_calendar_rest_time-11.0.1.0.0.99.dev5.dist-info/WHEEL
odoo11_addon_hr_calendar_rest_time-11.0.1.0.0.99.dev5.dist-info/top_level.txt
odoo11_addon_hr_calendar_rest_time-11.0.1.0.0.99.dev5.dist-info/RECORD
